LICENSE
MANIFEST.in
README.md
pyproject.toml
acemd/LICENSE
acemd/__init__.py
acemd/acemd.py
acemd/charmm.py
acemd/licensing.py
acemd/logging.ini
acemd/minimizer.py
acemd/nnp.py
acemd/protocols.py
acemd/reporters.py
acemd/restraints.py
acemd/utils.py
acemd/versionwarnings.py
acemd.egg-info/PKG-INFO
acemd.egg-info/SOURCES.txt
acemd.egg-info/dependency_links.txt
acemd.egg-info/entry_points.txt
acemd.egg-info/requires.txt
acemd.egg-info/top_level.txt
acemd/share/license-checker